lusid_express/__init__.py
lusid_express/__main__.py
lusid_express/load.le
lusid_express/apis/__init__.py
lusid_express/config/__init__.py
lusid_express/display/PRELOADED_VARS.md
lusid_express/display/__init__.py
lusid_express/utils/__init__.py
lusid_express/widgets/__init__.py
lusid_express-1.2.2.dist-info/LICENSE
lusid_express-1.2.2.dist-info/METADATA
lusid_express-1.2.2.dist-info/WHEEL
lusid_express-1.2.2.dist-info/top_level.txt
lusid_express-1.2.2.dist-info/RECORD
