Metadata-Version: 2.1
Name: lusid-express
Version: 1.2.2
Summary: lusid-express is a python package that makes it quick and easy to get started using Lusid and Luminesce.
Home-page: https://gitlab.com/orlando.calvo1/lusid-express
Author: Orlando Calvo
Author-email: orlando.calvo@finbourne.com
License: UNKNOWN
Platform: UNKNOWN
Classifier: Development Status :: 3 - Alpha
Classifier: Intended Audience :: Developers
Classifier: Topic :: Software Development :: Build Tools
Classifier: License :: OSI Approved :: MIT License
Classifier: Programming Language :: Python :: 3.9
License-File: LICENSE
Requires-Dist: pyyaml
Requires-Dist: lusid-bundle
